setup.cfg
setup.py
ootools/__init__.py
ootools.egg-info/PKG-INFO
ootools.egg-info/SOURCES.txt
ootools.egg-info/dependency_links.txt
ootools.egg-info/entry_points.txt
ootools.egg-info/not-zip-safe
ootools.egg-info/top_level.txt