Metadata-Version: 1.0
Name: ootools
Version: 0.1dev
Summary: Python and OpenOffice connectivity, and conversion tools.
Home-page: http://www.lucasmanual.com/mywiki/ootools
Author: Lukasz Szybalski
Author-email: szybalski@gmail.com
License: LGPL
Keywords: ootools,openoffice,python,pyuno,ods2csv,xls2csv
Platform: UNKNOWN
